plastron/handles/__init__.py
plastron/models/__init__.py
plastron/models/annotations.py
plastron/models/authorities.py
plastron/models/fedora.py
plastron/models/ldp.py
plastron/models/letter.py
plastron/models/newspaper.py
plastron/models/ore.py
plastron/models/page.py
plastron/models/pcdm.py
plastron/models/poster.py
plastron/models/umd.py
plastron/ocr/__init__.py
plastron/ocr/alto.py
plastron/ocr/core.py
plastron/ocr/hocr.py
plastron/rdf/__init__.py
plastron/rdf/authority.py
plastron/rdf/ldp.py
plastron/rdf/oa.py
plastron/rdf/ore.py
plastron/rdf/pcdm.py
plastron/rdf/rdf.py
plastron/serializers/__init__.py
plastron/serializers/csv.py
plastron/serializers/turtle.py
plastron/validation/__init__.py
plastron/validation/rules.py
plastron/validation/vocabularies/__init__.py
plastron/validation/vocabularies/dcmitype.ttl
plastron/validation/vocabularies/__pycache__/__init__.cpython-310.pyc
plastron/validation/vocabularies/__pycache__/__init__.cpython-311.pyc
plastron/validation/vocabularies/__pycache__/__init__.cpython-312.pyc
plastron/validation/vocabularies/__pycache__/__init__.cpython-38.pyc
plastron_models-4.6.2.dist-info/METADATA
plastron_models-4.6.2.dist-info/WHEEL
plastron_models-4.6.2.dist-info/entry_points.txt
plastron_models-4.6.2.dist-info/top_level.txt
plastron_models-4.6.2.dist-info/RECORD
