Metadata-Version: 2.4
Name: plastron-models
Version: 4.6.2
Summary: Content modelling built on the Plastron RDF to Python object mapper
Author-email: University of Maryland Libraries <lib-ssdr@umd.edu>, Josh Westgard <westgard@umd.edu>, Peter Eichman <peichman@umd.edu>, Mohamed Abdul Rasheed <mohideen@umd.edu>, Ben Wallberg <wallberg@umd.edu>, David Steelman <dsteelma@umd.edu>, Marc Andreu Grillo Aguilar <aguilarm@umd.edu>
Requires-Python: >=3.10
Requires-Dist: edtf_validate
Requires-Dist: importlib_metadata
Requires-Dist: lxml<6.0
Requires-Dist: requests
Requires-Dist: paramiko
Requires-Dist: pillow
Requires-Dist: plastron-client
Requires-Dist: plastron-rdf
Requires-Dist: plastron-utils
Requires-Dist: python-iso639
Requires-Dist: rdflib>=6.0.0
Requires-Dist: types-lxml
Provides-Extra: test
Requires-Dist: freezegun; extra == "test"
Requires-Dist: httpretty; extra == "test"
Requires-Dist: pytest; extra == "test"
Requires-Dist: pytest-cov; extra == "test"
